danatime/__init__.py
django_dana_time-0.1.0.dist-info/DESCRIPTION.rst
django_dana_time-0.1.0.dist-info/METADATA
django_dana_time-0.1.0.dist-info/metadata.json
django_dana_time-0.1.0.dist-info/RECORD
django_dana_time-0.1.0.dist-info/top_level.txt
django_dana_time-0.1.0.dist-info/WHEEL
